ultra/__init__.py
ultra/agent_pool.json
ultra/config.yaml
ultra/evaluate.py
ultra/rllib_train.py
ultra/train.py
ultra/baselines/__init__.py
ultra/baselines/adapter.py
ultra/baselines/agent_spec.py
ultra/baselines/bdqn/setup.py
ultra/baselines/bdqn/bdqn/__init__.py
ultra/baselines/bdqn/bdqn/explore.py
ultra/baselines/bdqn/bdqn/network.py
ultra/baselines/bdqn/bdqn/params.yaml
ultra/baselines/bdqn/bdqn/policy.py
ultra/baselines/common/__init__.py
ultra/baselines/common/baseline_state_preprocessor.py
ultra/baselines/common/replay_buffer.py
ultra/baselines/common/social_vehicle_config.py
ultra/baselines/common/social_vehicle_extraction.py
ultra/baselines/common/state_preprocessor.py
ultra/baselines/common/yaml_loader.py
ultra/baselines/common/social_vehicles_encoders/__init__.py
ultra/baselines/common/social_vehicles_encoders/pointnet_encoder.py
ultra/baselines/common/social_vehicles_encoders/pointnet_encoder_batched.py
ultra/baselines/common/social_vehicles_encoders/precog_encoder.py
ultra/baselines/dqn/setup.py
ultra/baselines/dqn/dqn/__init__.py
ultra/baselines/dqn/dqn/explore.py
ultra/baselines/dqn/dqn/network.py
ultra/baselines/dqn/dqn/params.yaml
ultra/baselines/dqn/dqn/policy.py
ultra/baselines/ppo/setup.py
ultra/baselines/ppo/ppo/__init__.py
ultra/baselines/ppo/ppo/network.py
ultra/baselines/ppo/ppo/params.yaml
ultra/baselines/ppo/ppo/policy.py
ultra/baselines/rllib/__init__.py
ultra/baselines/rllib/agent.py
ultra/baselines/rllib/models/fc_network.py
ultra/baselines/sac/setup.py
ultra/baselines/sac/sac/__init__.py
ultra/baselines/sac/sac/network.py
ultra/baselines/sac/sac/params.yaml
ultra/baselines/sac/sac/policy.py
ultra/baselines/td3/setup.py
ultra/baselines/td3/td3/cnn_models.py
ultra/baselines/td3/td3/config.py
ultra/baselines/td3/td3/fc_model.py
ultra/baselines/td3/td3/noise.py
ultra/baselines/td3/td3/params.yaml
ultra/baselines/td3/td3/policy.py
ultra/env/__init__.py
ultra/env/envision_base.sh
ultra/env/rllib_ultra_env.py
ultra/env/ultra_env.py
ultra_rl-0.2.0.dist-info/LICENSE
ultra_rl-0.2.0.dist-info/METADATA
ultra_rl-0.2.0.dist-info/WHEEL
ultra_rl-0.2.0.dist-info/top_level.txt
ultra_rl-0.2.0.dist-info/zip-safe
ultra_rl-0.2.0.dist-info/RECORD
