Metadata-Version: 2.1
Name: ultra-rl
Version: 0.2.0
Summary: Unprotected Left Turn for Robust Agents
Home-page: UNKNOWN
License: UNKNOWN
Platform: UNKNOWN
Requires-Python: >=3.7
Requires-Dist: smarts[test,train] (==0.4.14)
Requires-Dist: setuptools (!=50.0,>=41.0.0)
Requires-Dist: dill
Requires-Dist: black (==20.8b1)
Requires-Dist: ray[rllib] (==1.0.1.post1)
